MANIFEST.in
README.md
setup.py
stdeb.cfg
ckx_tools/__init__.py
ckx_tools/argument_parsing.py
ckx_tools/common.py
ckx_tools/config.py
ckx_tools/context.py
ckx_tools/metadata.py
ckx_tools/resultspace.py
ckx_tools/terminal_color.py
ckx_tools/utils.py
ckx_tools.egg-info/PKG-INFO
ckx_tools.egg-info/SOURCES.txt
ckx_tools.egg-info/dependency_links.txt
ckx_tools.egg-info/entry_points.txt
ckx_tools.egg-info/requires.txt
ckx_tools.egg-info/top_level.txt
ckx_tools/commands/__init__.py
ckx_tools/commands/catkin.py
ckx_tools/execution/__init__.py
ckx_tools/execution/controllers.py
ckx_tools/execution/events.py
ckx_tools/execution/executor.py
ckx_tools/execution/io.py
ckx_tools/execution/job_server.py
ckx_tools/execution/jobs.py
ckx_tools/execution/stages.py
ckx_tools/jobs/__init__.py
ckx_tools/jobs/catkin.py
ckx_tools/jobs/cmake.py
ckx_tools/jobs/output.py
ckx_tools/jobs/utils.py
ckx_tools/jobs/commands/__init__.py
ckx_tools/jobs/commands/cmake.py
ckx_tools/jobs/commands/make.py
ckx_tools/notifications/__init__.py
ckx_tools/notifications/impl.py
ckx_tools/notifications/resources/linux/ckx_icon.png
ckx_tools/notifications/resources/linux/ckx_icon_red.png
ckx_tools/notifications/resources/linux/ckx_icon_yellow.png
ckx_tools/notifications/resources/osx/catkin build.app/Contents/Info.plist
ckx_tools/notifications/resources/osx/catkin build.app/Contents/PkgInfo
ckx_tools/notifications/resources/osx/catkin build.app/Contents/MacOS/catkin build
ckx_tools/notifications/resources/osx/catkin build.app/Contents/Resources/AppIcon.icns
ckx_tools/notifications/resources/osx/catkin build.app/Contents/Resources/catkin_blue_logo_only.icns
ckx_tools/notifications/resources/osx/catkin build.app/Contents/Resources/en.lproj/Credits.rtf
ckx_tools/notifications/resources/osx/catkin build.app/Contents/Resources/en.lproj/InfoPlist.strings
ckx_tools/notifications/resources/osx/catkin build.app/Contents/Resources/en.lproj/MainMenu.nib
ckx_tools/verbs/__init__.py
ckx_tools/verbs/ckx_shell_verbs.bash
ckx_tools/verbs/ckx_build/__init__.py
ckx_tools/verbs/ckx_build/build.py
ckx_tools/verbs/ckx_build/cli.py
ckx_tools/verbs/ckx_build/color.py
ckx_tools/verbs/ckx_clean/__init__.py
