Metadata-Version: 1.1
Name: ckx-tools
Version: 0.5.17
Summary: 'X' tools for working with catkin.
Home-page: http://ckx-tools.readthedocs.org/
Author: Daniel Stonier
Author-email: d.stonier@gmail.com
License: Apache 2.0
Keywords: catkin
Platform: UNKNOWN
Classifier: Environment :: Console
Classifier: Intended Audience :: Developers
Classifier: License :: OSI Approved :: Apache Software License
Classifier: Programming Language :: Python
